fastapi_casbin_acl/__init__.py
fastapi_casbin_acl/cli.py
fastapi_casbin_acl/config.py
fastapi_casbin_acl/dependency.py
fastapi_casbin_acl/enforcer.py
fastapi_casbin_acl/exception_handlers.py
fastapi_casbin_acl/exceptions.py
fastapi_casbin_acl/models.py
fastapi_casbin_acl/registry.py
fastapi_casbin_acl/resource.py
fastapi_casbin_acl/schema.py
fastapi_casbin_acl/sync.py
fastapi_casbin_acl/utils.py
fastapi_casbin_acl/watcher.py
fastapi_casbin_acl/adapter/__init__.py
fastapi_casbin_acl/adapter/orm.py
fastapi_casbin_acl/adapter/sqlmodel_adapter.py
fastapi_casbin_acl/models/__init__.py
fastapi_casbin_acl/models/abac.conf
fastapi_casbin_acl/models/permission_rbac.conf
fastapi_casbin_acl/router/__init__.py
fastapi_casbin_acl/router/mappings.py
fastapi_casbin_acl/router/permissions.py
fastapi_casbin_acl/router/policies.py
fastapi_casbin_acl/router/reload.py
fastapi_casbin_acl/router/roles.py
fastapi_casbin_acl-0.2.0.dist-info/METADATA
fastapi_casbin_acl-0.2.0.dist-info/WHEEL
fastapi_casbin_acl-0.2.0.dist-info/entry_points.txt
fastapi_casbin_acl-0.2.0.dist-info/RECORD
