Metadata-Version: 2.4
Name: fastapi-casbin-acl
Version: 0.2.0
Summary: FastAPI permissions infrastructure dependency with RBAC+ABAC support using Casbin
Project-URL: Homepage, https://github.com/zxjlm/fastapi-casbin-acl
Project-URL: Repository, https://github.com/zxjlm/fastapi-casbin-acl
Author-email: harumonia <zxjlm233@gmail.com>
License: MIT
Classifier: Development Status :: 4 - Beta
Classifier: Framework :: FastAPI
Classifier: Intended Audience :: Developers
Classifier: License :: OSI Approved :: MIT License
Classifier: Programming Language :: Python :: 3.11
Classifier: Programming Language :: Python :: 3.12
Requires-Python: >=3.11
Requires-Dist: aiomysql>=0.2.0
Requires-Dist: casbin>=1.35.0
Requires-Dist: fastapi>=0.100.0
Requires-Dist: pydantic>=2.0.0
Requires-Dist: redis[hiredis]>=5.0.0
Requires-Dist: sqlalchemy[asyncio]>=2.0.0
Requires-Dist: sqlmodel>=0.0.22
Requires-Dist: typer>=0.9.0
Provides-Extra: dev
Requires-Dist: httpx>=0.24.0; extra == 'dev'
Requires-Dist: pytest>=7.0.0; extra == 'dev'
Requires-Dist: uvicorn>=0.22.0; extra == 'dev'
